<?xml version='1.0' encoding='utf-8'?><m:page id='722a19f8-0bf8-4847-bd4f-4f2cffea1a5a' xmlns='http://www.w3.org/1999/xhtml' title='Page Title' class='layout-atlas layout-atlas-responsive-default' url='/p/demo/dojo_aspect' xmlns:m='http://schemas.mendix.com/forms/1.0'><m:layouts><m:layout path='Atlas_UI_Resources/Atlas_Default.layout.xml'></m:layout></m:layouts><m:arguments><m:argument parameterName='8818112d-5a35-4af6-ae74-0413bb6abd7b'><div data-mendix-id='10_2' data-mendix-type='mxui.widget.DataGrid' data-mendix-props='"friendlyId":"Demo.DojoAspectDemo.grid1","entity":"Demo.Gank","schema":"f1ab7a75-f3cb-4699-be1a-71a6be01036c","config":{"locale":"en_US","gridType":"Standalone","gridpresentation":{"rows":20,"columns":1,"controlbar":true,"pagingbar":true,"searchbar":true,"waitforsearch":false,"selectionmode":"single","editable":false,"sortable":true,"refresh":0,"selectfirst":false,"showemptyrows":false},"datasource":{"friendlyId":"Demo.DojoAspectDemo.grid1","type":"database","path":"Demo.Gank","offlineConstraints":[],"xpathConstraints":""},"searchOptions":{"searchBar":true,"toggleable":true,"toggledByDefault":true},"searchElements":[{"searchInputName":"searchField1","defaults":null,"defaultsParser":"Simple","caption":"url","path":"url","operator":"contains"},{"searchInputName":"searchField2","defaults":null,"defaultsParser":"Simple","caption":"who","path":"who","operator":"contains"},{"searchInputName":"searchField3","defaults":null,"defaultsParser":"Simple","caption":"desc","path":"desc","operator":"contains"},{"searchInputName":"searchField4","defaults":null,"defaultsParser":"Simple","caption":"source","path":"source","operator":"contains"},{"searchInputName":"searchField5","defaults":null,"defaultsParser":"Simple","caption":"show type","path":"showType","operator":"contains"},{"searchInputName":"searchField6","defaults":null,"defaultsParser":"Simple","caption":"used","path":"used","operator":"=","retriever":"Bool"},{"searchInputName":"searchField7","defaults":null,"defaultsParser":"Simple","caption":"images URL","path":"imagesURL","operator":"contains"}],"controlBar":{"gridTools":[{"mxid":"10_0","friendlyId":"Demo.DojoAspectDemo.searchButton1","name":"searchButton1","caption":{"elements":["Search"],"friendlyId":"Demo.DojoAspectDemo.searchButton1"},"title":"","cssClass":"btn-default"},{"mxid":"10_1","friendlyId":"Demo.DojoAspectDemo.deleteButton1","name":"deleteButton1","caption":{"elements":["Delete"],"friendlyId":"Demo.DojoAspectDemo.deleteButton1"},"title":"","cssClass":"btn-default","visibleForRoles":["Administrator","User","Tester"]}],"gridActions":[{"keyValue":"10_0","gridFunction":"ToggleSearch"},{"keyValue":"10_1","gridFunction":"DeleteSelection"}]},"griddata":[{"tag":"url","name":"column3","editable":false,"render":"String","display":{"width":"14%","string":"url"}},{"tag":"who","name":"column4","editable":false,"render":"String","display":{"width":"14%","string":"who"}},{"tag":"desc","name":"column5","editable":false,"render":"String","display":{"width":"14%","string":"desc"}},{"tag":"source","name":"column6","editable":false,"render":"String","display":{"width":"14%","string":"source"}},{"tag":"showType","name":"column7","editable":false,"render":"String","display":{"width":"14%","string":"show type"}},{"tag":"used","name":"column8","editable":false,"render":"Boolean","display":{"width":"15%","string":"used"}},{"tag":"imagesURL","name":"column9","editable":false,"render":"String","display":{"width":"15%","string":"images URL"}}],"plugins":{}}' class='mx-datagrid mx-name-grid1' tabindex='0'></div><div data-mendix-id='10_3' data-mendix-type='HTMLSnippet.widget.HTMLSnippet' data-mendix-props='"friendlyId":"Demo.DojoAspectDemo.hTMLSnippet1","contenttype":"js","contents":"\r\nvar datagrid=dijit.registry.byNode($(\".mx-name-grid1\")[0]);\r\nrequire([\"dojo/aspect\"], function(aspect){\r\n    aspect.after(datagrid, \"refreshGrid\", function(){\r\n\r\n        $.each($(\".mx-name-column6 .mx-datagrid-data-wrapper\"), function (indexInArray, valueOfElement) { \r\n             if($(this).text()==&apos;chrome&apos;){\r\n                 $(this).css(\"color\",&apos;red&apos;);\r\n             }else if($(this).text()==&apos;web&apos;){\r\n                 $(this).css(\"color\",&apos;blue&apos;);\r\n             }else\r\n             {\r\n                $(this).css(\"color\",&apos;pink&apos;);\r\n             }\r\n        });\r\n     \r\n    });\r\n  });","contentsPath":"","onclickmf":"","documentation":"","refreshOnContextChange":false,"refreshOnContextUpdate":false,"encloseHTMLWithDiv":true' class='mx-name-hTMLSnippet1' tabindex='0'></div></m:argument></m:arguments></m:page>