<?xml version='1.0' encoding='utf-8'?><m:page id='bab1e4aa-6706-4a35-b85e-847070129ba2' xmlns='http://www.w3.org/1999/xhtml' title='Select Selector1' xmlns:m='http://schemas.mendix.com/forms/1.0'><m:layouts><m:layout path='ExcelImporter/ExcelImporterPopup.layout.xml'></m:layout></m:layouts><m:arguments><m:argument parameterName='e7dceaed-8987-40c7-86c5-d21b9e8ab812'><div data-mendix-id='23_0' data-mendix-type='mxui.widget.ListView' data-mendix-props='"friendlyId":"Demo.Selector1_Select.listView1","hasSearch":true,"datasource":{"queryId":"RkHTDf0x30ihHozpc8KcCA","hasParameter":false,"searchPaths":["dataName","otherData"],"friendlyId":"Demo.Selector1_Select.listView1","type":"database","path":"Demo.Selector1","offlineConstraints":[]},"page":10,"selectable":"","action":{"type":"doNothing","argMap":{},"config":{}},"templateMap":{"Demo.Selector1":"Demo.Selector1"}' class='mx-name-listView1'></div></m:argument></m:arguments><m:templates><m:template widget-id='23_0' name='Demo.Selector1'><div data-mendix-id='23_1' data-mendix-type='mxui.widget.DataView' data-mendix-props='"friendlyId":"Demo.Selector1_Select.listView1","entity":"Demo.Selector1","schema":"e77ee5df-3247-411b-a0b2-fa13f5622527","readOnly":true,"datasource":{"friendlyId":"Demo.Selector1_Select.listView1","type":"direct","path":"Demo.Selector1"}' tabindex='0'></div></m:template><m:template widget-id='23_1' name='content'><div data-mendix-id='23_2' class='form-group mx-name-textBox1'><label class='control-label'>data name</label><div data-mendix-id='23_4' data-mendix-type='mxui.widget.TextInput' data-mendix-props='"friendlyId":"Demo.Selector1_Select.textBox1","insideFormGroup":true,"attributePath":"Demo.Selector1/dataName","readOnlyStyle":"text","validation":null,"events":{"change":{"type":"doNothing","argMap":{},"config":{}},"focus":{"type":"doNothing","argMap":{},"config":{}},"blur":{"type":"doNothing","argMap":{},"config":{}}},"placeholder":"","maxLength":200' tabindex='0'></div></div><div data-mendix-id='23_3' class='form-group mx-name-textBox2'><label class='control-label'>other data</label><div data-mendix-id='23_5' data-mendix-type='mxui.widget.TextInput' data-mendix-props='"friendlyId":"Demo.Selector1_Select.textBox2","insideFormGroup":true,"attributePath":"Demo.Selector1/otherData","readOnlyStyle":"text","validation":null,"events":{"change":{"type":"doNothing","argMap":{},"config":{}},"focus":{"type":"doNothing","argMap":{},"config":{}},"blur":{"type":"doNothing","argMap":{},"config":{}}},"placeholder":"","maxLength":200' tabindex='0'></div></div></m:template></m:templates></m:page>