<?xml version='1.0' encoding='utf-8'?><m:page id='a6499131-c8f1-4d74-ac8d-f6612850653e' xmlns='http://www.w3.org/1999/xhtml' title='Page Title' class='layout-atlas layout-atlas-responsive-default' xmlns:m='http://schemas.mendix.com/forms/1.0'><m:layouts><m:layout path='Atlas_UI_Resources/Atlas_Default.layout.xml'></m:layout></m:layouts><m:arguments><m:argument parameterName='8818112d-5a35-4af6-ae74-0413bb6abd7b'><div data-mendix-id='0_0' class='mx-layoutgrid mx-layoutgrid-fluid container-fluid mx-name-layoutGrid2'><div class='row'><div class='col-md-12'><div class='mx-name-container1'><div data-mendix-id='0_1' data-mendix-type='mxui.widget.ReactWidgetWrapper' data-mendix-props='"widgetTree":[{"widget":"com.mendix.widget.core.Text","widgetId":"0_1","props":{"name":"text1","class":"mx-name-text1","style":{},"caption":{"$type":"DynamicTextProperty","scope":"$pageParameter","template":{"elements":["请畅所欲言吧"],"friendlyId":"Articles.Home.text1"}},"renderMode":"h2"}}]'></div></div></div></div></div><div data-mendix-id='0_2' class='mx-layoutgrid mx-layoutgrid-fluid container-fluid mx-name-layoutGrid1'><div class='row'><div class='col-md-12'><div data-mendix-id='0_3' data-mendix-type='mxui.widget.DataView' data-mendix-props='"friendlyId":"Articles.Home.dataView1","entity":"Articles.Article","schema":"bf5c6e21-2d82-4941-b8a7-b718d6ae626b","datasource":{"friendlyId":"Articles.Home.dataView1","type":"microflow","microflow":"Articles.CreateEmptyArticle","path":"Articles.Article","parameters":[]}' class='mx-name-dataView1 form-horizontal' tabindex='0'></div></div></div></div></m:argument></m:arguments><m:templates><m:template widget-id='0_3' name='content'><table class='mx-table mx-name-table1'><colgroup><col style='width:15%'></col><col style='width:85%'></col></colgroup><tbody><tr><td style='text-align: right; vertical-align: middle;'><div data-mendix-id='0_6' data-mendix-type='mxui.widget.ReactWidgetWrapper' data-mendix-props='"widgetTree":[{"widget":"com.mendix.widget.core.Text","widgetId":"0_6","props":{"name":"text2","class":"mx-name-text2","style":{},"caption":{"$type":"DynamicTextProperty","scope":"0_3","template":{"elements":["标题"],"friendlyId":"Articles.Home.text2"}},"renderMode":"span"}}]'></div></td><td><div data-mendix-id='0_8' class='mx-name-textBox1'><div data-mendix-id='0_22' data-mendix-type='mxui.widget.TextInput' data-mendix-props='"friendlyId":"Articles.Home.textBox1","insideFormGroup":false,"attributePath":"Articles.Article/Title","readOnlyStyle":"control","validation":null,"events":{"change":{"type":"doNothing","argMap":{},"config":{}},"focus":{"type":"doNothing","argMap":{},"config":{}},"blur":{"type":"doNothing","argMap":{},"config":{}}},"placeholder":"","maxLength":200' tabindex='0'></div></div></td></tr><tr><td colspan='2'><div data-mendix-id='0_10' class='mx-name-textArea1'><div data-mendix-id='0_23' data-mendix-type='mxui.widget.TextArea' data-mendix-props='"friendlyId":"Articles.Home.textArea1","insideFormGroup":false,"attributePath":"Articles.Article/Content","readOnlyStyle":"control","validation":null,"events":{"change":{"type":"doNothing","argMap":{},"config":{}},"focus":{"type":"doNothing","argMap":{},"config":{}},"blur":{"type":"doNothing","argMap":{},"config":{}}},"placeholder":"","rows":5' tabindex='0'></div></div></td></tr><tr><td style='text-align: right; vertical-align: middle;'><div data-mendix-id='0_12' data-mendix-type='mxui.widget.ReactWidgetWrapper' data-mendix-props='"widgetTree":[{"widget":"com.mendix.widget.core.Text","widgetId":"0_12","props":{"name":"text3","class":"mx-name-text3","style":{},"caption":{"$type":"DynamicTextProperty","scope":"0_3","template":{"elements":["文章分类"],"friendlyId":"Articles.Home.text3"}},"renderMode":"span"}}]'></div></td><td><div data-mendix-id='0_14' data-mendix-type='mxui.widget.InputReferenceSetSelector' data-mendix-props='"friendlyId":"Articles.Home.referenceSetSelector1","insideFormGroup":false,"attributePath":"Articles.Article/Articles.Article_SearchItem/Demo.SearchItem/Category","readOnlyStyle":"control","attributePath":"Articles.Article/Articles.Article_SearchItem/Demo.SearchItem/Category","datasource":{"friendlyId":"Articles.Home.referenceSetSelector1","type":"xpath","path":"Demo.SearchItem","constrainedBy":[]},"selectPageSettings":{"name":"Demo/SearchItem_Select.page.xml","location":"modal","resizable":true},"events":{"change":{"type":"doNothing","argMap":{},"config":{}}}' class='mx-name-referenceSetSelector1' tabindex='0'></div></td></tr></tbody></table></m:template><m:template widget-id='0_3' name='footer'><div data-mendix-id='0_20' data-mendix-type='mxui.widget.ActionButton' data-mendix-props='"friendlyId":"Articles.Home.actionButton1","caption":{"elements":["Save"],"friendlyId":"Articles.Home.actionButton1"},"renderType":"button","action":{"type":"saveChanges","argMap":{"object":"0_3"},"config":{"closePage":true}},"disableDuringAction":true' class='mx-name-actionButton1 btn-success' tabindex='0'></div><div data-mendix-id='0_21' data-mendix-type='mxui.widget.ActionButton' data-mendix-props='"friendlyId":"Articles.Home.actionButton2","caption":{"elements":["Cancel"],"friendlyId":"Articles.Home.actionButton2"},"renderType":"button","action":{"type":"cancelChanges","argMap":{},"config":{"closePage":true}},"disableDuringAction":true' class='mx-name-actionButton2 btn-default' tabindex='0'></div></m:template></m:templates></m:page>