<?xml version='1.0' encoding='utf-8'?><m:page id='32ecfa0a-c505-4159-a63e-b6627d38220c' xmlns='http://www.w3.org/1999/xhtml' title='Trainee NewEdit' xmlns:m='http://schemas.mendix.com/forms/1.0'><m:layouts><m:layout path='Atlas_UI_Resources/PopupLayout.layout.xml'></m:layout></m:layouts><m:arguments><m:argument parameterName='b0dba8bb-678a-4113-b77a-7aefca10dc13'><div data-mendix-id='1_0' class='mx-layoutgrid mx-layoutgrid-fluid container-fluid mx-name-layoutGrid1'><div class='row'><div class='col-md-12'><div data-mendix-id='1_1' data-mendix-type='mxui.widget.DataView' data-mendix-props='"friendlyId":"MyFirstModule.Trainee_NewEdit.dataView6","entity":"MyFirstModule.Trainee","schema":"d28d080e-c2d2-45b5-a4a8-ed1f2a4bdde6","datasource":{"friendlyId":"MyFirstModule.Trainee_NewEdit.dataView6","type":"direct","path":"MyFirstModule.Trainee"}' class='mx-name-dataView6' tabindex='0'></div></div></div></div></m:argument></m:arguments><m:templates><m:template widget-id='1_1' name='content'><div data-mendix-id='1_2' class='form-group mx-name-textBox1'><label class='control-label'>Name</label><div data-mendix-id='1_7' data-mendix-type='mxui.widget.TextInput' data-mendix-props='"friendlyId":"MyFirstModule.Trainee_NewEdit.textBox1","insideFormGroup":true,"attributePath":"MyFirstModule.Trainee/Name","readOnlyStyle":"control","validation":null,"events":{"change":{"type":"doNothing","argMap":{},"config":{}},"focus":{"type":"doNothing","argMap":{},"config":{}},"blur":{"type":"doNothing","argMap":{},"config":{}}},"placeholder":""' tabindex='0'></div></div><div data-mendix-id='1_3' class='form-group mx-name-textArea1'><label class='control-label'>Address</label><div data-mendix-id='1_8' data-mendix-type='mxui.widget.TextArea' data-mendix-props='"friendlyId":"MyFirstModule.Trainee_NewEdit.textArea1","insideFormGroup":true,"attributePath":"MyFirstModule.Trainee/Address","readOnlyStyle":"control","validation":null,"events":{"change":{"type":"doNothing","argMap":{},"config":{}},"focus":{"type":"doNothing","argMap":{},"config":{}},"blur":{"type":"doNothing","argMap":{},"config":{}}},"placeholder":"","rows":5' tabindex='0'></div></div><div data-mendix-id='1_4' class='form-group mx-name-textBox3'><label class='control-label'>Email address</label><div data-mendix-id='1_9' data-mendix-type='mxui.widget.TextInput' data-mendix-props='"friendlyId":"MyFirstModule.Trainee_NewEdit.textBox3","insideFormGroup":true,"attributePath":"MyFirstModule.Trainee/EmailAddress","readOnlyStyle":"control","validation":null,"events":{"change":{"type":"doNothing","argMap":{},"config":{}},"focus":{"type":"doNothing","argMap":{},"config":{}},"blur":{"type":"doNothing","argMap":{},"config":{}}},"placeholder":""' tabindex='0'></div></div></m:template><m:template widget-id='1_1' name='footer'><div data-mendix-id='1_5' data-mendix-type='mxui.widget.ActionButton' data-mendix-props='"friendlyId":"MyFirstModule.Trainee_NewEdit.actionButton1","caption":{"elements":["Save"],"friendlyId":"MyFirstModule.Trainee_NewEdit.actionButton1"},"renderType":"button","action":{"type":"saveChanges","argMap":{"object":"1_1"},"config":{"closePage":true}},"disableDuringAction":true' class='mx-name-actionButton1 btn-success' tabindex='0'></div><div data-mendix-id='1_6' data-mendix-type='mxui.widget.ActionButton' data-mendix-props='"friendlyId":"MyFirstModule.Trainee_NewEdit.actionButton2","caption":{"elements":["Cancel"],"friendlyId":"MyFirstModule.Trainee_NewEdit.actionButton2"},"renderType":"button","action":{"type":"cancelChanges","argMap":{},"config":{"closePage":true}},"disableDuringAction":true' class='mx-name-actionButton2 btn-default' tabindex='0'></div></m:template></m:templates></m:page>