<?xml version='1.0' encoding='utf-8'?><m:page id='8936d980-b390-4f42-8d52-ac6d39682384' xmlns='http://www.w3.org/1999/xhtml' title='Edit Mx column' closeButton='122_0' xmlns:m='http://schemas.mendix.com/forms/1.0'><m:layouts><m:layout path='XLSReport/PopupLayout.layout.xml'></m:layout></m:layouts><m:arguments><m:argument parameterName='1b679c77-3f9f-4b01-8a9f-4a204a096301'><div data-mendix-id='122_1' data-mendix-type='mxui.widget.DataView' data-mendix-props='"friendlyId":"XLSReport.MxColumn_NewEdit.dataView1","entity":"XLSReport.MxColumn","schema":"0e2de1ba-1fa1-4aa7-833e-1ddc758145d2","datasource":{"friendlyId":"XLSReport.MxColumn_NewEdit.dataView1","type":"direct","path":"XLSReport.MxColumn"},"conditions":{"122_49":{"visible":{"type":"variable","variable":"currentObject","path":"DataAggregate"}},"122_51":{"visible":{"type":"variable","variable":"currentObject","path":"ResultAggregate"}}}' class='mx-name-dataView1' tabindex='0'></div></m:argument></m:arguments><m:templates><m:template widget-id='122_1' name='content'><table class='mx-table mx-name-table1'><colgroup><col style='width:20%'></col><col style='width:30%'></col><col style='width:20%'></col><col style='width:30%'></col></colgroup><tbody><tr><th><label class='mx-name-label2' data-mendix-id='122_4'>Column number</label></th><td><div data-mendix-id='122_6' class='mx-name-textBox2'><div data-mendix-id='122_53' data-mendix-type='mxui.widget.NumberInput' data-mendix-props='"friendlyId":"XLSReport.MxColumn_NewEdit.textBox2","insideFormGroup":false,"attributePath":"XLSReport.MxColumn/ColumnNumber","readOnlyStyle":"text","validation":null,"events":{"change":{"type":"doNothing","argMap":{},"config":{}},"focus":{"type":"doNothing","argMap":{},"config":{}},"blur":{"type":"doNothing","argMap":{},"config":{}}},"placeholder":""' tabindex='0'></div></div></td><th><label class='mx-name-label11' data-mendix-id='122_8'>Style</label></th><td><div data-mendix-id='122_10' data-mendix-type='mxui.widget.ReferenceSelector' data-mendix-props='"friendlyId":"XLSReport.MxColumn_NewEdit.referenceSelector6","insideFormGroup":false,"attributePath":"XLSReport.MxColumn/XLSReport.MxData_MxCellStyle/XLSReport.MxCellStyle/Name","readOnlyStyle":"text","attributePath":"XLSReport.MxColumn/XLSReport.MxData_MxCellStyle/XLSReport.MxCellStyle/Name","datasource":{"friendlyId":"XLSReport.MxColumn_NewEdit.referenceSelector6","type":"xpath","path":"XLSReport.MxCellStyle","constrainedBy":["XLSReport.MxColumn/XLSReport.MxData_MxSheet/XLSReport.MxSheet/XLSReport.MxSheet_Template/XLSReport.MxTemplate/XLSReport.MxCellStyle_Template/XLSReport.MxCellStyle"],"sort":[["Name","asc"]]},"events":{"change":{"type":"doNothing","argMap":{},"config":{}}},"validation":null,"emptyOptionCaption":""' class='mx-name-referenceSelector6' tabindex='0'></div></td></tr><tr><th><label class='mx-name-label3' data-mendix-id='122_12'>Name</label></th><td><div data-mendix-id='122_14' class='mx-name-textBox1'><div data-mendix-id='122_54' data-mendix-type='mxui.widget.TextInput' data-mendix-props='"friendlyId":"XLSReport.MxColumn_NewEdit.textBox1","insideFormGroup":false,"attributePath":"XLSReport.MxColumn/Name","readOnlyStyle":"text","validation":null,"events":{"change":{"type":"doNothing","argMap":{},"config":{}},"focus":{"type":"doNothing","argMap":{},"config":{}},"blur":{"type":"doNothing","argMap":{},"config":{}}},"placeholder":"","maxLength":200' tabindex='0'></div></div></td><th><label class='mx-name-label6' data-mendix-id='122_16'>Use name as column header</label></th><td><div data-mendix-id='122_18' data-mendix-type='mxui.widget.BoolSelect' data-mendix-props='"friendlyId":"XLSReport.MxColumn_NewEdit.checkBox1","insideFormGroup":false,"attributePath":"XLSReport.MxColumn/NameAsHeader","readOnlyStyle":"text","validation":null,"events":{"change":{"type":"doNothing","argMap":{},"config":{}},"focus":{"type":"doNothing","argMap":{},"config":{}},"blur":{"type":"doNothing","argMap":{},"config":{}}}' class='mx-name-checkBox1' tabindex='0'></div></td></tr><tr><td class='nopadding ' colspan='4'><div data-mendix-id='122_20' data-mendix-type='mxui.widget.DataView' data-mendix-props='"friendlyId":"XLSReport.MxColumn_NewEdit.dataView4","entity":"XLSReport.MxXPath","schema":"c23e767d-397a-4302-9825-8d1b5abdd065","hideFooter":true,"datasource":{"friendlyId":"XLSReport.MxColumn_NewEdit.dataView4","type":"direct","path":"XLSReport.MxXPath_MxData/XLSReport.MxXPath"},"conditions":{"122_77":{"visible":{"type":"function","name":"=","parameters":[{"type":"variable","variable":"currentObject","path":"RetrieveType"},{"type":"literal","value":"Attribute"}]}},"122_78":{"visible":{"type":"function","name":"=","parameters":[{"type":"variable","variable":"currentObject","path":"RetrieveType"},{"type":"literal","value":"Reference"}]}},"122_79":{"visible":{"type":"function","name":"=","parameters":[{"type":"variable","variable":"currentObject","path":"RetrieveType"},{"type":"literal","value":"Reference"}]}},"122_80":{"visible":{"type":"variable","variable":"currentObject","path":"SubVisible"}}}' class='mx-name-dataView4' tabindex='0'></div></td></tr><tr><th><label class='mx-name-label7' data-mendix-id='122_22'>Aggregate on attribute</label></th><td colspan='3'><div data-mendix-id='122_24' data-mendix-type='mxui.widget.BoolSelect' data-mendix-props='"friendlyId":"XLSReport.MxColumn_NewEdit.checkBox3","insideFormGroup":false,"attributePath":"XLSReport.MxColumn/DataAggregate","readOnlyStyle":"text","validation":null,"events":{"change":{"type":"doNothing","argMap":{},"config":{}},"focus":{"type":"doNothing","argMap":{},"config":{}},"blur":{"type":"doNothing","argMap":{},"config":{}}}' class='mx-name-checkBox3' tabindex='0'></div></td></tr><tr data-mendix-id='122_49'><th><label class='mx-name-label8' data-mendix-id='122_26'>Aggregate type</label></th><td><div data-mendix-id='122_28' data-mendix-type='mxui.widget.EnumSelect' data-mendix-props='"friendlyId":"XLSReport.MxColumn_NewEdit.dropDown2","insideFormGroup":false,"attributePath":"XLSReport.MxColumn/DataAggregateFunction","readOnlyStyle":"text","validation":null,"events":{"change":{"type":"doNothing","argMap":{},"config":{}},"focus":{"type":"doNothing","argMap":{},"config":{}},"blur":{"type":"doNothing","argMap":{},"config":{}}},"emptyOptionCaption":""' class='mx-name-dropDown2' tabindex='0'></div></td><td colspan='2'><label class='mx-name-label9' data-mendix-id='122_30'>The aggregate will be added in the query</label></td></tr><tr><th><label class='mx-name-label1' data-mendix-id='122_32'>End column with aggregate</label></th><td colspan='3'><div data-mendix-id='122_34' data-mendix-type='mxui.widget.BoolSelect' data-mendix-props='"friendlyId":"XLSReport.MxColumn_NewEdit.checkBox2","insideFormGroup":false,"attributePath":"XLSReport.MxColumn/ResultAggregate","readOnlyStyle":"text","validation":null,"events":{"change":{"type":"doNothing","argMap":{},"config":{}},"focus":{"type":"doNothing","argMap":{},"config":{}},"blur":{"type":"doNothing","argMap":{},"config":{}}}' class='mx-name-checkBox2' tabindex='0'></div></td></tr><tr data-mendix-id='122_51'><th><label class='mx-name-label4' data-mendix-id='122_36'>Aggregate type</label></th><td><div data-mendix-id='122_38' data-mendix-type='mxui.widget.EnumSelect' data-mendix-props='"friendlyId":"XLSReport.MxColumn_NewEdit.dropDown1","insideFormGroup":false,"attributePath":"XLSReport.MxColumn/ResultAggregateFunction","readOnlyStyle":"text","validation":null,"events":{"change":{"type":"doNothing","argMap":{},"config":{}},"focus":{"type":"doNothing","argMap":{},"config":{}},"blur":{"type":"doNothing","argMap":{},"config":{}}},"emptyOptionCaption":""' class='mx-name-dropDown1' tabindex='0'></div></td><td colspan='2'><label class='mx-name-label5' data-mendix-id='122_40'>The value of the aggregate will on the bottom of the results</label></td></tr></tbody></table></m:template><m:template widget-id='122_1' name='footer'><div data-mendix-id='122_52' data-mendix-type='mxui.widget.ActionButton' data-mendix-props='"friendlyId":"XLSReport.MxColumn_NewEdit.microflowButton1","caption":{"elements":["Save"],"friendlyId":"XLSReport.MxColumn_NewEdit.microflowButton1"},"iconUrl":"img/System$Save.png?636820633452992334","renderType":"button","action":{"type":"callMicroflow","argMap":{"MxColumn":"122_1"},"config":{"name":"XLSReport.IVK_Column_Save","applyTo":"selection","allowedRoles":["Administrator","User","Tester","DemoAdmin"]}},"disableDuringAction":true' data-mendix-roles='Administrator,User,Tester,DemoAdmin' class='mx-name-microflowButton1 btn-default' tabindex='0'></div><div data-mendix-id='122_0' data-mendix-type='mxui.widget.ActionButton' data-mendix-props='"friendlyId":"XLSReport.MxColumn_NewEdit.cancelButton1","caption":{"elements":["Cancel"],"friendlyId":"XLSReport.MxColumn_NewEdit.cancelButton1"},"iconUrl":"img/System$Cancel.png?636820633452992334","renderType":"button","action":{"type":"cancelChanges","argMap":{},"config":{"closePage":false}},"disableDuringAction":true' class='mx-name-cancelButton1 btn-default' tabindex='0'></div></m:template><m:template widget-id='122_20' name='content'><table class='mx-table mx-name-table5'><colgroup><col style='width:25%'></col><col style='width:75%'></col></colgroup><tbody><tr><th><label class='mx-name-label17' data-mendix-id='122_57'>Retrieve type</label></th><td><div data-mendix-id='122_59' data-mendix-type='mxui.widget.EnumSelect' data-mendix-props='"friendlyId":"XLSReport.MxColumn_NewEdit.dropDown3","insideFormGroup":false,"attributePath":"XLSReport.MxXPath/RetrieveType","readOnlyStyle":"text","validation":null,"events":{"change":{"type":"callMicroflow","argMap":{"ParentMxXPath":"122_20"},"config":{"name":"XLSReport.OCh_Xpath_RetrieveType","validate":"node","applyTo":"selection","allowedRoles":["Administrator","User","Tester","DemoAdmin"]}},"focus":{"type":"doNothing","argMap":{},"config":{}},"blur":{"type":"doNothing","argMap":{},"config":{}}},"emptyOptionCaption":""' class='mx-name-dropDown3' tabindex='0'></div></td></tr><tr data-mendix-id='122_77'><th><label class='mx-name-label18' data-mendix-id='122_61'>Select attribute</label></th><td><div data-mendix-id='122_63' data-mendix-type='mxui.widget.ReferenceSelector' data-mendix-props='"friendlyId":"XLSReport.MxColumn_NewEdit.referenceSelector4","insideFormGroup":false,"attributePath":"XLSReport.MxXPath/XLSReport.MxXPath_MxObjectMember/MxModelReflection.MxObjectMember/AttributeName","readOnlyStyle":"text","attributePath":"XLSReport.MxXPath/XLSReport.MxXPath_MxObjectMember/MxModelReflection.MxObjectMember/AttributeName","datasource":{"friendlyId":"XLSReport.MxColumn_NewEdit.referenceSelector4","type":"microflow","microflow":"XLSReport.DS_First_Attribute","path":"MxModelReflection.MxObjectMember"},"events":{"change":{"type":"doNothing","argMap":{},"config":{}}},"validation":null,"emptyOptionCaption":""' class='mx-name-referenceSelector4' tabindex='0'></div></td></tr><tr data-mendix-id='122_78'><th><label class='mx-name-label19' data-mendix-id='122_65'>Select reference</label></th><td><div data-mendix-id='122_67' data-mendix-type='mxui.widget.ReferenceSelector' data-mendix-props='"friendlyId":"XLSReport.MxColumn_NewEdit.referenceSelector2","insideFormGroup":false,"attributePath":"XLSReport.MxXPath/XLSReport.MxXPath_MxObjectReference/MxModelReflection.MxObjectReference/CompleteName","readOnlyStyle":"text","attributePath":"XLSReport.MxXPath/XLSReport.MxXPath_MxObjectReference/MxModelReflection.MxObjectReference/CompleteName","datasource":{"friendlyId":"XLSReport.MxColumn_NewEdit.referenceSelector2","type":"microflow","microflow":"XLSReport.DS_First_Reference","path":"MxModelReflection.MxObjectReference"},"events":{"change":{"type":"doNothing","argMap":{},"config":{}}},"validation":null,"emptyOptionCaption":""' class='mx-name-referenceSelector2' tabindex='0'></div></td></tr><tr data-mendix-id='122_79'><th><label class='mx-name-label20' data-mendix-id='122_69'>Select object</label></th><td><div data-mendix-id='122_71' data-mendix-type='mxui.widget.ReferenceSelector' data-mendix-props='"friendlyId":"XLSReport.MxColumn_NewEdit.referenceSelector3","insideFormGroup":false,"attributePath":"XLSReport.MxXPath/XLSReport.MxXPath_MxObjectType/MxModelReflection.MxObjectType/CompleteName","readOnlyStyle":"text","attributePath":"XLSReport.MxXPath/XLSReport.MxXPath_MxObjectType/MxModelReflection.MxObjectType/CompleteName","datasource":{"friendlyId":"XLSReport.MxColumn_NewEdit.referenceSelector3","type":"xpath","path":"MxModelReflection.MxObjectType","constrainedBy":["XLSReport.MxXPath/XLSReport.MxXPath_MxObjectReference/MxModelReflection.MxObjectReference/MxModelReflection.MxObjectReference_MxObjectType/MxModelReflection.MxObjectType"],"sort":[["CompleteName","asc"]]},"events":{"change":{"type":"callMicroflow","argMap":{"MxXPath":"122_20"},"config":{"name":"XLSReport.OCh_XPath_Refresh","validate":"node","applyTo":"selection","allowedRoles":["Administrator","User","Tester","DemoAdmin"]}}},"validation":null,"emptyOptionCaption":""' class='mx-name-referenceSelector3' tabindex='0'></div></td></tr><tr data-mendix-id='122_80'><td colspan='2'><div data-mendix-id='122_73' data-mendix-type='mxui.widget.DataView' data-mendix-props='"friendlyId":"XLSReport.MxColumn_NewEdit.dataView5","entity":"XLSReport.MxXPath","schema":"36ce8556-c261-4d8c-87ee-828d1ab86e39","hideFooter":true,"datasource":{"friendlyId":"XLSReport.MxColumn_NewEdit.dataView5","type":"direct","path":"XLSReport.MxXPath_ParentMxXPath/XLSReport.MxXPath"},"conditions":{"122_81_82_106":{"visible":{"type":"function","name":"=","parameters":[{"type":"variable","variable":"currentObject","path":"RetrieveType"},{"type":"literal","value":"Attribute"}]}},"122_81_82_107":{"visible":{"type":"function","name":"=","parameters":[{"type":"variable","variable":"currentObject","path":"RetrieveType"},{"type":"literal","value":"Attribute"}]}},"122_81_82_108":{"visible":{"type":"function","name":"=","parameters":[{"type":"variable","variable":"currentObject","path":"RetrieveType"},{"type":"literal","value":"Reference"}]}},"122_81_82_109":{"visible":{"type":"function","name":"=","parameters":[{"type":"variable","variable":"currentObject","path":"RetrieveType"},{"type":"literal","value":"Reference"}]}},"122_81_110":{"visible":{"type":"variable","variable":"currentObject","path":"SubVisible"}}}' class='mx-name-dataView5' tabindex='0'></div></td></tr></tbody></table></m:template><m:template widget-id='122_73' name='content'><table class='mx-table mx-name-table1'><colgroup><col style='width:25%'></col><col style='width:75%'></col></colgroup><tbody><tr><th><label class='mx-name-label1' data-mendix-id='122_81_82_85'>Retrieve type</label></th><td><div data-mendix-id='122_81_82_87' data-mendix-type='mxui.widget.EnumSelect' data-mendix-props='"friendlyId":"XLSReport.SN_Xpath_Template.dropDown1","insideFormGroup":false,"attributePath":"XLSReport.MxXPath/RetrieveType","readOnlyStyle":"text","validation":null,"events":{"change":{"type":"callMicroflow","argMap":{"ParentMxXPath":"122_73"},"config":{"name":"XLSReport.OCh_Xpath_RetrieveType","validate":"node","applyTo":"selection","allowedRoles":["Administrator","User","Tester","DemoAdmin"]}},"focus":{"type":"doNothing","argMap":{},"config":{}},"blur":{"type":"doNothing","argMap":{},"config":{}}},"emptyOptionCaption":""' class='mx-name-dropDown1' tabindex='0'></div></td></tr><tr data-mendix-id='122_81_82_106'><th><label class='mx-name-label2' data-mendix-id='122_81_82_89'>Select attribute</label></th><td><div data-mendix-id='122_81_82_91' data-mendix-type='mxui.widget.ReferenceSelector' data-mendix-props='"friendlyId":"XLSReport.SN_Xpath_Template.referenceSelector1","insideFormGroup":false,"attributePath":"XLSReport.MxXPath/XLSReport.MxXPath_MxObjectMember/MxModelReflection.MxObjectMember/AttributeName","readOnlyStyle":"text","attributePath":"XLSReport.MxXPath/XLSReport.MxXPath_MxObjectMember/MxModelReflection.MxObjectMember/AttributeName","datasource":{"friendlyId":"XLSReport.SN_Xpath_Template.referenceSelector1","type":"microflow","microflow":"XLSReport.DS_Attribute","path":"MxModelReflection.MxObjectMember"},"events":{"change":{"type":"doNothing","argMap":{},"config":{}}},"validation":null,"emptyOptionCaption":""' class='mx-name-referenceSelector1' tabindex='0'></div></td></tr><tr data-mendix-id='122_81_82_107'><td></td><td><label class='mx-name-label5' data-mendix-id='122_81_82_94'>Virtual attributes can't be used, because those attributes can't be retrieved with OQL</label></td></tr><tr data-mendix-id='122_81_82_108'><th><label class='mx-name-label3' data-mendix-id='122_81_82_96'>Select reference</label></th><td><div data-mendix-id='122_81_82_98' data-mendix-type='mxui.widget.ReferenceSelector' data-mendix-props='"friendlyId":"XLSReport.SN_Xpath_Template.referenceSelector2","insideFormGroup":false,"attributePath":"XLSReport.MxXPath/XLSReport.MxXPath_MxObjectReference/MxModelReflection.MxObjectReference/CompleteName","readOnlyStyle":"text","attributePath":"XLSReport.MxXPath/XLSReport.MxXPath_MxObjectReference/MxModelReflection.MxObjectReference/CompleteName","datasource":{"friendlyId":"XLSReport.SN_Xpath_Template.referenceSelector2","type":"microflow","microflow":"XLSReport.DS_Reference","path":"MxModelReflection.MxObjectReference"},"events":{"change":{"type":"doNothing","argMap":{},"config":{}}},"validation":null,"emptyOptionCaption":""' class='mx-name-referenceSelector2' tabindex='0'></div></td></tr><tr data-mendix-id='122_81_82_109'><th><label class='mx-name-label4' data-mendix-id='122_81_82_100'>Select object</label></th><td><div data-mendix-id='122_81_82_102' data-mendix-type='mxui.widget.ReferenceSelector' data-mendix-props='"friendlyId":"XLSReport.SN_Xpath_Template.referenceSelector3","insideFormGroup":false,"attributePath":"XLSReport.MxXPath/XLSReport.MxXPath_MxObjectType/MxModelReflection.MxObjectType/CompleteName","readOnlyStyle":"text","attributePath":"XLSReport.MxXPath/XLSReport.MxXPath_MxObjectType/MxModelReflection.MxObjectType/CompleteName","datasource":{"friendlyId":"XLSReport.SN_Xpath_Template.referenceSelector3","type":"xpath","path":"MxModelReflection.MxObjectType","constrainedBy":["XLSReport.MxXPath/XLSReport.MxXPath_MxObjectReference/MxModelReflection.MxObjectReference/MxModelReflection.MxObjectReference_MxObjectType/MxModelReflection.MxObjectType"],"sort":[["CompleteName","asc"]]},"events":{"change":{"type":"callMicroflow","argMap":{"MxXPath":"122_73"},"config":{"name":"XLSReport.OCh_XPath_Refresh","validate":"node","applyTo":"selection","allowedRoles":["Administrator","User","Tester","DemoAdmin"]}}},"validation":null,"emptyOptionCaption":""' class='mx-name-referenceSelector3' tabindex='0'></div></td></tr></tbody></table><div data-mendix-id='122_81_110' data-mendix-type='mxui.widget.DataView' data-mendix-props='"friendlyId":"XLSReport.SN_Xpath_MASTER.dataView2","entity":"XLSReport.MxXPath","schema":"0b0b1a46-0bd5-4ceb-8d95-29ca2024d192","datasource":{"friendlyId":"XLSReport.SN_Xpath_MASTER.dataView2","type":"direct","path":"XLSReport.MxXPath_ParentMxXPath/XLSReport.MxXPath"},"conditions":{"122_81_111_112_106":{"visible":{"type":"function","name":"=","parameters":[{"type":"variable","variable":"currentObject","path":"RetrieveType"},{"type":"literal","value":"Attribute"}]}},"122_81_111_112_107":{"visible":{"type":"function","name":"=","parameters":[{"type":"variable","variable":"currentObject","path":"RetrieveType"},{"type":"literal","value":"Attribute"}]}},"122_81_111_112_108":{"visible":{"type":"function","name":"=","parameters":[{"type":"variable","variable":"currentObject","path":"RetrieveType"},{"type":"literal","value":"Reference"}]}},"122_81_111_112_109":{"visible":{"type":"function","name":"=","parameters":[{"type":"variable","variable":"currentObject","path":"RetrieveType"},{"type":"literal","value":"Reference"}]}},"122_81_111_113":{"visible":{"type":"variable","variable":"currentObject","path":"SubVisible"}}}' class='mx-name-dataView2' tabindex='0'></div></m:template><m:template widget-id='122_81_110' name='content'><table class='mx-table mx-name-table1'><colgroup><col style='width:25%'></col><col style='width:75%'></col></colgroup><tbody><tr><th><label class='mx-name-label1' data-mendix-id='122_81_111_112_85'>Retrieve type</label></th><td><div data-mendix-id='122_81_111_112_87' data-mendix-type='mxui.widget.EnumSelect' data-mendix-props='"friendlyId":"XLSReport.SN_Xpath_Template.dropDown1","insideFormGroup":false,"attributePath":"XLSReport.MxXPath/RetrieveType","readOnlyStyle":"text","validation":null,"events":{"change":{"type":"callMicroflow","argMap":{"ParentMxXPath":"122_81_110"},"config":{"name":"XLSReport.OCh_Xpath_RetrieveType","validate":"node","applyTo":"selection","allowedRoles":["Administrator","User","Tester","DemoAdmin"]}},"focus":{"type":"doNothing","argMap":{},"config":{}},"blur":{"type":"doNothing","argMap":{},"config":{}}},"emptyOptionCaption":""' class='mx-name-dropDown1' tabindex='0'></div></td></tr><tr data-mendix-id='122_81_111_112_106'><th><label class='mx-name-label2' data-mendix-id='122_81_111_112_89'>Select attribute</label></th><td><div data-mendix-id='122_81_111_112_91' data-mendix-type='mxui.widget.ReferenceSelector' data-mendix-props='"friendlyId":"XLSReport.SN_Xpath_Template.referenceSelector1","insideFormGroup":false,"attributePath":"XLSReport.MxXPath/XLSReport.MxXPath_MxObjectMember/MxModelReflection.MxObjectMember/AttributeName","readOnlyStyle":"text","attributePath":"XLSReport.MxXPath/XLSReport.MxXPath_MxObjectMember/MxModelReflection.MxObjectMember/AttributeName","datasource":{"friendlyId":"XLSReport.SN_Xpath_Template.referenceSelector1","type":"microflow","microflow":"XLSReport.DS_Attribute","path":"MxModelReflection.MxObjectMember"},"events":{"change":{"type":"doNothing","argMap":{},"config":{}}},"validation":null,"emptyOptionCaption":""' class='mx-name-referenceSelector1' tabindex='0'></div></td></tr><tr data-mendix-id='122_81_111_112_107'><td></td><td><label class='mx-name-label5' data-mendix-id='122_81_111_112_94'>Virtual attributes can't be used, because those attributes can't be retrieved with OQL</label></td></tr><tr data-mendix-id='122_81_111_112_108'><th><label class='mx-name-label3' data-mendix-id='122_81_111_112_96'>Select reference</label></th><td><div data-mendix-id='122_81_111_112_98' data-mendix-type='mxui.widget.ReferenceSelector' data-mendix-props='"friendlyId":"XLSReport.SN_Xpath_Template.referenceSelector2","insideFormGroup":false,"attributePath":"XLSReport.MxXPath/XLSReport.MxXPath_MxObjectReference/MxModelReflection.MxObjectReference/CompleteName","readOnlyStyle":"text","attributePath":"XLSReport.MxXPath/XLSReport.MxXPath_MxObjectReference/MxModelReflection.MxObjectReference/CompleteName","datasource":{"friendlyId":"XLSReport.SN_Xpath_Template.referenceSelector2","type":"microflow","microflow":"XLSReport.DS_Reference","path":"MxModelReflection.MxObjectReference"},"events":{"change":{"type":"doNothing","argMap":{},"config":{}}},"validation":null,"emptyOptionCaption":""' class='mx-name-referenceSelector2' tabindex='0'></div></td></tr><tr data-mendix-id='122_81_111_112_109'><th><label class='mx-name-label4' data-mendix-id='122_81_111_112_100'>Select object</label></th><td><div data-mendix-id='122_81_111_112_102' data-mendix-type='mxui.widget.ReferenceSelector' data-mendix-props='"friendlyId":"XLSReport.SN_Xpath_Template.referenceSelector3","insideFormGroup":false,"attributePath":"XLSReport.MxXPath/XLSReport.MxXPath_MxObjectType/MxModelReflection.MxObjectType/CompleteName","readOnlyStyle":"text","attributePath":"XLSReport.MxXPath/XLSReport.MxXPath_MxObjectType/MxModelReflection.MxObjectType/CompleteName","datasource":{"friendlyId":"XLSReport.SN_Xpath_Template.referenceSelector3","type":"xpath","path":"MxModelReflection.MxObjectType","constrainedBy":["XLSReport.MxXPath/XLSReport.MxXPath_MxObjectReference/MxModelReflection.MxObjectReference/MxModelReflection.MxObjectReference_MxObjectType/MxModelReflection.MxObjectType"],"sort":[["CompleteName","asc"]]},"events":{"change":{"type":"callMicroflow","argMap":{"MxXPath":"122_81_110"},"config":{"name":"XLSReport.OCh_XPath_Refresh","validate":"node","applyTo":"selection","allowedRoles":["Administrator","User","Tester","DemoAdmin"]}}},"validation":null,"emptyOptionCaption":""' class='mx-name-referenceSelector3' tabindex='0'></div></td></tr></tbody></table><div data-mendix-id='122_81_111_113' data-mendix-type='mxui.widget.DataView' data-mendix-props='"friendlyId":"XLSReport.SN_Xpath_2.dataView2","entity":"XLSReport.MxXPath","schema":"8c52c40f-d858-494a-8b85-f7050aa0fa3f","datasource":{"friendlyId":"XLSReport.SN_Xpath_2.dataView2","type":"direct","path":"XLSReport.MxXPath_ParentMxXPath/XLSReport.MxXPath"},"conditions":{"122_81_111_114_115_106":{"visible":{"type":"function","name":"=","parameters":[{"type":"variable","variable":"currentObject","path":"RetrieveType"},{"type":"literal","value":"Attribute"}]}},"122_81_111_114_115_107":{"visible":{"type":"function","name":"=","parameters":[{"type":"variable","variable":"currentObject","path":"RetrieveType"},{"type":"literal","value":"Attribute"}]}},"122_81_111_114_115_108":{"visible":{"type":"function","name":"=","parameters":[{"type":"variable","variable":"currentObject","path":"RetrieveType"},{"type":"literal","value":"Reference"}]}},"122_81_111_114_115_109":{"visible":{"type":"function","name":"=","parameters":[{"type":"variable","variable":"currentObject","path":"RetrieveType"},{"type":"literal","value":"Reference"}]}},"122_81_111_114_116":{"visible":{"type":"variable","variable":"currentObject","path":"SubVisible"}}}' class='mx-name-dataView2' tabindex='0'></div></m:template><m:template widget-id='122_81_111_113' name='content'><table class='mx-table mx-name-table1'><colgroup><col style='width:25%'></col><col style='width:75%'></col></colgroup><tbody><tr><th><label class='mx-name-label1' data-mendix-id='122_81_111_114_115_85'>Retrieve type</label></th><td><div data-mendix-id='122_81_111_114_115_87' data-mendix-type='mxui.widget.EnumSelect' data-mendix-props='"friendlyId":"XLSReport.SN_Xpath_Template.dropDown1","insideFormGroup":false,"attributePath":"XLSReport.MxXPath/RetrieveType","readOnlyStyle":"text","validation":null,"events":{"change":{"type":"callMicroflow","argMap":{"ParentMxXPath":"122_81_111_113"},"config":{"name":"XLSReport.OCh_Xpath_RetrieveType","validate":"node","applyTo":"selection","allowedRoles":["Administrator","User","Tester","DemoAdmin"]}},"focus":{"type":"doNothing","argMap":{},"config":{}},"blur":{"type":"doNothing","argMap":{},"config":{}}},"emptyOptionCaption":""' class='mx-name-dropDown1' tabindex='0'></div></td></tr><tr data-mendix-id='122_81_111_114_115_106'><th><label class='mx-name-label2' data-mendix-id='122_81_111_114_115_89'>Select attribute</label></th><td><div data-mendix-id='122_81_111_114_115_91' data-mendix-type='mxui.widget.ReferenceSelector' data-mendix-props='"friendlyId":"XLSReport.SN_Xpath_Template.referenceSelector1","insideFormGroup":false,"attributePath":"XLSReport.MxXPath/XLSReport.MxXPath_MxObjectMember/MxModelReflection.MxObjectMember/AttributeName","readOnlyStyle":"text","attributePath":"XLSReport.MxXPath/XLSReport.MxXPath_MxObjectMember/MxModelReflection.MxObjectMember/AttributeName","datasource":{"friendlyId":"XLSReport.SN_Xpath_Template.referenceSelector1","type":"microflow","microflow":"XLSReport.DS_Attribute","path":"MxModelReflection.MxObjectMember"},"events":{"change":{"type":"doNothing","argMap":{},"config":{}}},"validation":null,"emptyOptionCaption":""' class='mx-name-referenceSelector1' tabindex='0'></div></td></tr><tr data-mendix-id='122_81_111_114_115_107'><td></td><td><label class='mx-name-label5' data-mendix-id='122_81_111_114_115_94'>Virtual attributes can't be used, because those attributes can't be retrieved with OQL</label></td></tr><tr data-mendix-id='122_81_111_114_115_108'><th><label class='mx-name-label3' data-mendix-id='122_81_111_114_115_96'>Select reference</label></th><td><div data-mendix-id='122_81_111_114_115_98' data-mendix-type='mxui.widget.ReferenceSelector' data-mendix-props='"friendlyId":"XLSReport.SN_Xpath_Template.referenceSelector2","insideFormGroup":false,"attributePath":"XLSReport.MxXPath/XLSReport.MxXPath_MxObjectReference/MxModelReflection.MxObjectReference/CompleteName","readOnlyStyle":"text","attributePath":"XLSReport.MxXPath/XLSReport.MxXPath_MxObjectReference/MxModelReflection.MxObjectReference/CompleteName","datasource":{"friendlyId":"XLSReport.SN_Xpath_Template.referenceSelector2","type":"microflow","microflow":"XLSReport.DS_Reference","path":"MxModelReflection.MxObjectReference"},"events":{"change":{"type":"doNothing","argMap":{},"config":{}}},"validation":null,"emptyOptionCaption":""' class='mx-name-referenceSelector2' tabindex='0'></div></td></tr><tr data-mendix-id='122_81_111_114_115_109'><th><label class='mx-name-label4' data-mendix-id='122_81_111_114_115_100'>Select object</label></th><td><div data-mendix-id='122_81_111_114_115_102' data-mendix-type='mxui.widget.ReferenceSelector' data-mendix-props='"friendlyId":"XLSReport.SN_Xpath_Template.referenceSelector3","insideFormGroup":false,"attributePath":"XLSReport.MxXPath/XLSReport.MxXPath_MxObjectType/MxModelReflection.MxObjectType/CompleteName","readOnlyStyle":"text","attributePath":"XLSReport.MxXPath/XLSReport.MxXPath_MxObjectType/MxModelReflection.MxObjectType/CompleteName","datasource":{"friendlyId":"XLSReport.SN_Xpath_Template.referenceSelector3","type":"xpath","path":"MxModelReflection.MxObjectType","constrainedBy":["XLSReport.MxXPath/XLSReport.MxXPath_MxObjectReference/MxModelReflection.MxObjectReference/MxModelReflection.MxObjectReference_MxObjectType/MxModelReflection.MxObjectType"],"sort":[["CompleteName","asc"]]},"events":{"change":{"type":"callMicroflow","argMap":{"MxXPath":"122_81_111_113"},"config":{"name":"XLSReport.OCh_XPath_Refresh","validate":"node","applyTo":"selection","allowedRoles":["Administrator","User","Tester","DemoAdmin"]}}},"validation":null,"emptyOptionCaption":""' class='mx-name-referenceSelector3' tabindex='0'></div></td></tr></tbody></table><div data-mendix-id='122_81_111_114_116' data-mendix-type='mxui.widget.DataView' data-mendix-props='"friendlyId":"XLSReport.SN_Xpath_3.dataView2","entity":"XLSReport.MxXPath","schema":"efa53a44-87ee-4870-a5c7-99c96f4ea173","datasource":{"friendlyId":"XLSReport.SN_Xpath_3.dataView2","type":"direct","path":"XLSReport.MxXPath_ParentMxXPath/XLSReport.MxXPath"},"conditions":{"122_81_111_114_117_118_106":{"visible":{"type":"function","name":"=","parameters":[{"type":"variable","variable":"currentObject","path":"RetrieveType"},{"type":"literal","value":"Attribute"}]}},"122_81_111_114_117_118_107":{"visible":{"type":"function","name":"=","parameters":[{"type":"variable","variable":"currentObject","path":"RetrieveType"},{"type":"literal","value":"Attribute"}]}},"122_81_111_114_117_118_108":{"visible":{"type":"function","name":"=","parameters":[{"type":"variable","variable":"currentObject","path":"RetrieveType"},{"type":"literal","value":"Reference"}]}},"122_81_111_114_117_118_109":{"visible":{"type":"function","name":"=","parameters":[{"type":"variable","variable":"currentObject","path":"RetrieveType"},{"type":"literal","value":"Reference"}]}},"122_81_111_114_117_119":{"visible":{"type":"variable","variable":"currentObject","path":"SubVisible"}}}' class='mx-name-dataView2' tabindex='0'></div></m:template><m:template widget-id='122_81_111_114_116' name='content'><table class='mx-table mx-name-table1'><colgroup><col style='width:25%'></col><col style='width:75%'></col></colgroup><tbody><tr><th><label class='mx-name-label1' data-mendix-id='122_81_111_114_117_118_85'>Retrieve type</label></th><td><div data-mendix-id='122_81_111_114_117_118_87' data-mendix-type='mxui.widget.EnumSelect' data-mendix-props='"friendlyId":"XLSReport.SN_Xpath_Template.dropDown1","insideFormGroup":false,"attributePath":"XLSReport.MxXPath/RetrieveType","readOnlyStyle":"text","validation":null,"events":{"change":{"type":"callMicroflow","argMap":{"ParentMxXPath":"122_81_111_114_116"},"config":{"name":"XLSReport.OCh_Xpath_RetrieveType","validate":"node","applyTo":"selection","allowedRoles":["Administrator","User","Tester","DemoAdmin"]}},"focus":{"type":"doNothing","argMap":{},"config":{}},"blur":{"type":"doNothing","argMap":{},"config":{}}},"emptyOptionCaption":""' class='mx-name-dropDown1' tabindex='0'></div></td></tr><tr data-mendix-id='122_81_111_114_117_118_106'><th><label class='mx-name-label2' data-mendix-id='122_81_111_114_117_118_89'>Select attribute</label></th><td><div data-mendix-id='122_81_111_114_117_118_91' data-mendix-type='mxui.widget.ReferenceSelector' data-mendix-props='"friendlyId":"XLSReport.SN_Xpath_Template.referenceSelector1","insideFormGroup":false,"attributePath":"XLSReport.MxXPath/XLSReport.MxXPath_MxObjectMember/MxModelReflection.MxObjectMember/AttributeName","readOnlyStyle":"text","attributePath":"XLSReport.MxXPath/XLSReport.MxXPath_MxObjectMember/MxModelReflection.MxObjectMember/AttributeName","datasource":{"friendlyId":"XLSReport.SN_Xpath_Template.referenceSelector1","type":"microflow","microflow":"XLSReport.DS_Attribute","path":"MxModelReflection.MxObjectMember"},"events":{"change":{"type":"doNothing","argMap":{},"config":{}}},"validation":null,"emptyOptionCaption":""' class='mx-name-referenceSelector1' tabindex='0'></div></td></tr><tr data-mendix-id='122_81_111_114_117_118_107'><td></td><td><label class='mx-name-label5' data-mendix-id='122_81_111_114_117_118_94'>Virtual attributes can't be used, because those attributes can't be retrieved with OQL</label></td></tr><tr data-mendix-id='122_81_111_114_117_118_108'><th><label class='mx-name-label3' data-mendix-id='122_81_111_114_117_118_96'>Select reference</label></th><td><div data-mendix-id='122_81_111_114_117_118_98' data-mendix-type='mxui.widget.ReferenceSelector' data-mendix-props='"friendlyId":"XLSReport.SN_Xpath_Template.referenceSelector2","insideFormGroup":false,"attributePath":"XLSReport.MxXPath/XLSReport.MxXPath_MxObjectReference/MxModelReflection.MxObjectReference/CompleteName","readOnlyStyle":"text","attributePath":"XLSReport.MxXPath/XLSReport.MxXPath_MxObjectReference/MxModelReflection.MxObjectReference/CompleteName","datasource":{"friendlyId":"XLSReport.SN_Xpath_Template.referenceSelector2","type":"microflow","microflow":"XLSReport.DS_Reference","path":"MxModelReflection.MxObjectReference"},"events":{"change":{"type":"doNothing","argMap":{},"config":{}}},"validation":null,"emptyOptionCaption":""' class='mx-name-referenceSelector2' tabindex='0'></div></td></tr><tr data-mendix-id='122_81_111_114_117_118_109'><th><label class='mx-name-label4' data-mendix-id='122_81_111_114_117_118_100'>Select object</label></th><td><div data-mendix-id='122_81_111_114_117_118_102' data-mendix-type='mxui.widget.ReferenceSelector' data-mendix-props='"friendlyId":"XLSReport.SN_Xpath_Template.referenceSelector3","insideFormGroup":false,"attributePath":"XLSReport.MxXPath/XLSReport.MxXPath_MxObjectType/MxModelReflection.MxObjectType/CompleteName","readOnlyStyle":"text","attributePath":"XLSReport.MxXPath/XLSReport.MxXPath_MxObjectType/MxModelReflection.MxObjectType/CompleteName","datasource":{"friendlyId":"XLSReport.SN_Xpath_Template.referenceSelector3","type":"xpath","path":"MxModelReflection.MxObjectType","constrainedBy":["XLSReport.MxXPath/XLSReport.MxXPath_MxObjectReference/MxModelReflection.MxObjectReference/MxModelReflection.MxObjectReference_MxObjectType/MxModelReflection.MxObjectType"],"sort":[["CompleteName","asc"]]},"events":{"change":{"type":"callMicroflow","argMap":{"MxXPath":"122_81_111_114_116"},"config":{"name":"XLSReport.OCh_XPath_Refresh","validate":"node","applyTo":"selection","allowedRoles":["Administrator","User","Tester","DemoAdmin"]}}},"validation":null,"emptyOptionCaption":""' class='mx-name-referenceSelector3' tabindex='0'></div></td></tr></tbody></table><div data-mendix-id='122_81_111_114_117_119' data-mendix-type='mxui.widget.DataView' data-mendix-props='"friendlyId":"XLSReport.SN_Xpath_4.dataView2","entity":"XLSReport.MxXPath","schema":"212f9462-1a18-4163-8c2d-f6cc5cdf908c","datasource":{"friendlyId":"XLSReport.SN_Xpath_4.dataView2","type":"direct","path":"XLSReport.MxXPath_ParentMxXPath/XLSReport.MxXPath"},"conditions":{"122_81_111_114_117_120_121_106":{"visible":{"type":"function","name":"=","parameters":[{"type":"variable","variable":"currentObject","path":"RetrieveType"},{"type":"literal","value":"Attribute"}]}},"122_81_111_114_117_120_121_107":{"visible":{"type":"function","name":"=","parameters":[{"type":"variable","variable":"currentObject","path":"RetrieveType"},{"type":"literal","value":"Attribute"}]}},"122_81_111_114_117_120_121_108":{"visible":{"type":"function","name":"=","parameters":[{"type":"variable","variable":"currentObject","path":"RetrieveType"},{"type":"literal","value":"Reference"}]}},"122_81_111_114_117_120_121_109":{"visible":{"type":"function","name":"=","parameters":[{"type":"variable","variable":"currentObject","path":"RetrieveType"},{"type":"literal","value":"Reference"}]}},"122_81_111_114_117_120_122":{"visible":{"type":"variable","variable":"currentObject","path":"SubVisible"}}}' class='mx-name-dataView2' tabindex='0'></div></m:template><m:template widget-id='122_81_111_114_117_119' name='content'><table class='mx-table mx-name-table1'><colgroup><col style='width:25%'></col><col style='width:75%'></col></colgroup><tbody><tr><th><label class='mx-name-label1' data-mendix-id='122_81_111_114_117_120_121_85'>Retrieve type</label></th><td><div data-mendix-id='122_81_111_114_117_120_121_87' data-mendix-type='mxui.widget.EnumSelect' data-mendix-props='"friendlyId":"XLSReport.SN_Xpath_Template.dropDown1","insideFormGroup":false,"attributePath":"XLSReport.MxXPath/RetrieveType","readOnlyStyle":"text","validation":null,"events":{"change":{"type":"callMicroflow","argMap":{"ParentMxXPath":"122_81_111_114_117_119"},"config":{"name":"XLSReport.OCh_Xpath_RetrieveType","validate":"node","applyTo":"selection","allowedRoles":["Administrator","User","Tester","DemoAdmin"]}},"focus":{"type":"doNothing","argMap":{},"config":{}},"blur":{"type":"doNothing","argMap":{},"config":{}}},"emptyOptionCaption":""' class='mx-name-dropDown1' tabindex='0'></div></td></tr><tr data-mendix-id='122_81_111_114_117_120_121_106'><th><label class='mx-name-label2' data-mendix-id='122_81_111_114_117_120_121_89'>Select attribute</label></th><td><div data-mendix-id='122_81_111_114_117_120_121_91' data-mendix-type='mxui.widget.ReferenceSelector' data-mendix-props='"friendlyId":"XLSReport.SN_Xpath_Template.referenceSelector1","insideFormGroup":false,"attributePath":"XLSReport.MxXPath/XLSReport.MxXPath_MxObjectMember/MxModelReflection.MxObjectMember/AttributeName","readOnlyStyle":"text","attributePath":"XLSReport.MxXPath/XLSReport.MxXPath_MxObjectMember/MxModelReflection.MxObjectMember/AttributeName","datasource":{"friendlyId":"XLSReport.SN_Xpath_Template.referenceSelector1","type":"microflow","microflow":"XLSReport.DS_Attribute","path":"MxModelReflection.MxObjectMember"},"events":{"change":{"type":"doNothing","argMap":{},"config":{}}},"validation":null,"emptyOptionCaption":""' class='mx-name-referenceSelector1' tabindex='0'></div></td></tr><tr data-mendix-id='122_81_111_114_117_120_121_107'><td></td><td><label class='mx-name-label5' data-mendix-id='122_81_111_114_117_120_121_94'>Virtual attributes can't be used, because those attributes can't be retrieved with OQL</label></td></tr><tr data-mendix-id='122_81_111_114_117_120_121_108'><th><label class='mx-name-label3' data-mendix-id='122_81_111_114_117_120_121_96'>Select reference</label></th><td><div data-mendix-id='122_81_111_114_117_120_121_98' data-mendix-type='mxui.widget.ReferenceSelector' data-mendix-props='"friendlyId":"XLSReport.SN_Xpath_Template.referenceSelector2","insideFormGroup":false,"attributePath":"XLSReport.MxXPath/XLSReport.MxXPath_MxObjectReference/MxModelReflection.MxObjectReference/CompleteName","readOnlyStyle":"text","attributePath":"XLSReport.MxXPath/XLSReport.MxXPath_MxObjectReference/MxModelReflection.MxObjectReference/CompleteName","datasource":{"friendlyId":"XLSReport.SN_Xpath_Template.referenceSelector2","type":"microflow","microflow":"XLSReport.DS_Reference","path":"MxModelReflection.MxObjectReference"},"events":{"change":{"type":"doNothing","argMap":{},"config":{}}},"validation":null,"emptyOptionCaption":""' class='mx-name-referenceSelector2' tabindex='0'></div></td></tr><tr data-mendix-id='122_81_111_114_117_120_121_109'><th><label class='mx-name-label4' data-mendix-id='122_81_111_114_117_120_121_100'>Select object</label></th><td><div data-mendix-id='122_81_111_114_117_120_121_102' data-mendix-type='mxui.widget.ReferenceSelector' data-mendix-props='"friendlyId":"XLSReport.SN_Xpath_Template.referenceSelector3","insideFormGroup":false,"attributePath":"XLSReport.MxXPath/XLSReport.MxXPath_MxObjectType/MxModelReflection.MxObjectType/CompleteName","readOnlyStyle":"text","attributePath":"XLSReport.MxXPath/XLSReport.MxXPath_MxObjectType/MxModelReflection.MxObjectType/CompleteName","datasource":{"friendlyId":"XLSReport.SN_Xpath_Template.referenceSelector3","type":"xpath","path":"MxModelReflection.MxObjectType","constrainedBy":["XLSReport.MxXPath/XLSReport.MxXPath_MxObjectReference/MxModelReflection.MxObjectReference/MxModelReflection.MxObjectReference_MxObjectType/MxModelReflection.MxObjectType"],"sort":[["CompleteName","asc"]]},"events":{"change":{"type":"callMicroflow","argMap":{"MxXPath":"122_81_111_114_117_119"},"config":{"name":"XLSReport.OCh_XPath_Refresh","validate":"node","applyTo":"selection","allowedRoles":["Administrator","User","Tester","DemoAdmin"]}}},"validation":null,"emptyOptionCaption":""' class='mx-name-referenceSelector3' tabindex='0'></div></td></tr></tbody></table><div data-mendix-id='122_81_111_114_117_120_122' data-mendix-type='mxui.widget.DataView' data-mendix-props='"friendlyId":"XLSReport.SN_Xpath_5.dataView2","entity":"XLSReport.MxXPath","schema":"40b9fcd8-5d62-499c-ac15-16896cbac44b","datasource":{"friendlyId":"XLSReport.SN_Xpath_5.dataView2","type":"direct","path":"XLSReport.MxXPath_ParentMxXPath/XLSReport.MxXPath"},"conditions":{"122_81_111_114_117_120_123_106":{"visible":{"type":"function","name":"=","parameters":[{"type":"variable","variable":"currentObject","path":"RetrieveType"},{"type":"literal","value":"Attribute"}]}},"122_81_111_114_117_120_123_107":{"visible":{"type":"function","name":"=","parameters":[{"type":"variable","variable":"currentObject","path":"RetrieveType"},{"type":"literal","value":"Attribute"}]}},"122_81_111_114_117_120_123_108":{"visible":{"type":"function","name":"=","parameters":[{"type":"variable","variable":"currentObject","path":"RetrieveType"},{"type":"literal","value":"Reference"}]}},"122_81_111_114_117_120_123_109":{"visible":{"type":"function","name":"=","parameters":[{"type":"variable","variable":"currentObject","path":"RetrieveType"},{"type":"literal","value":"Reference"}]}}}' class='mx-name-dataView2' tabindex='0'></div></m:template><m:template widget-id='122_81_111_114_117_120_122' name='content'><table class='mx-table mx-name-table1'><colgroup><col style='width:25%'></col><col style='width:75%'></col></colgroup><tbody><tr><th><label class='mx-name-label1' data-mendix-id='122_81_111_114_117_120_123_85'>Retrieve type</label></th><td><div data-mendix-id='122_81_111_114_117_120_123_87' data-mendix-type='mxui.widget.EnumSelect' data-mendix-props='"friendlyId":"XLSReport.SN_Xpath_Template.dropDown1","insideFormGroup":false,"attributePath":"XLSReport.MxXPath/RetrieveType","readOnlyStyle":"text","validation":null,"events":{"change":{"type":"callMicroflow","argMap":{"ParentMxXPath":"122_81_111_114_117_120_122"},"config":{"name":"XLSReport.OCh_Xpath_RetrieveType","validate":"node","applyTo":"selection","allowedRoles":["Administrator","User","Tester","DemoAdmin"]}},"focus":{"type":"doNothing","argMap":{},"config":{}},"blur":{"type":"doNothing","argMap":{},"config":{}}},"emptyOptionCaption":""' class='mx-name-dropDown1' tabindex='0'></div></td></tr><tr data-mendix-id='122_81_111_114_117_120_123_106'><th><label class='mx-name-label2' data-mendix-id='122_81_111_114_117_120_123_89'>Select attribute</label></th><td><div data-mendix-id='122_81_111_114_117_120_123_91' data-mendix-type='mxui.widget.ReferenceSelector' data-mendix-props='"friendlyId":"XLSReport.SN_Xpath_Template.referenceSelector1","insideFormGroup":false,"attributePath":"XLSReport.MxXPath/XLSReport.MxXPath_MxObjectMember/MxModelReflection.MxObjectMember/AttributeName","readOnlyStyle":"text","attributePath":"XLSReport.MxXPath/XLSReport.MxXPath_MxObjectMember/MxModelReflection.MxObjectMember/AttributeName","datasource":{"friendlyId":"XLSReport.SN_Xpath_Template.referenceSelector1","type":"microflow","microflow":"XLSReport.DS_Attribute","path":"MxModelReflection.MxObjectMember"},"events":{"change":{"type":"doNothing","argMap":{},"config":{}}},"validation":null,"emptyOptionCaption":""' class='mx-name-referenceSelector1' tabindex='0'></div></td></tr><tr data-mendix-id='122_81_111_114_117_120_123_107'><td></td><td><label class='mx-name-label5' data-mendix-id='122_81_111_114_117_120_123_94'>Virtual attributes can't be used, because those attributes can't be retrieved with OQL</label></td></tr><tr data-mendix-id='122_81_111_114_117_120_123_108'><th><label class='mx-name-label3' data-mendix-id='122_81_111_114_117_120_123_96'>Select reference</label></th><td><div data-mendix-id='122_81_111_114_117_120_123_98' data-mendix-type='mxui.widget.ReferenceSelector' data-mendix-props='"friendlyId":"XLSReport.SN_Xpath_Template.referenceSelector2","insideFormGroup":false,"attributePath":"XLSReport.MxXPath/XLSReport.MxXPath_MxObjectReference/MxModelReflection.MxObjectReference/CompleteName","readOnlyStyle":"text","attributePath":"XLSReport.MxXPath/XLSReport.MxXPath_MxObjectReference/MxModelReflection.MxObjectReference/CompleteName","datasource":{"friendlyId":"XLSReport.SN_Xpath_Template.referenceSelector2","type":"microflow","microflow":"XLSReport.DS_Reference","path":"MxModelReflection.MxObjectReference"},"events":{"change":{"type":"doNothing","argMap":{},"config":{}}},"validation":null,"emptyOptionCaption":""' class='mx-name-referenceSelector2' tabindex='0'></div></td></tr><tr data-mendix-id='122_81_111_114_117_120_123_109'><th><label class='mx-name-label4' data-mendix-id='122_81_111_114_117_120_123_100'>Select object</label></th><td><div data-mendix-id='122_81_111_114_117_120_123_102' data-mendix-type='mxui.widget.ReferenceSelector' data-mendix-props='"friendlyId":"XLSReport.SN_Xpath_Template.referenceSelector3","insideFormGroup":false,"attributePath":"XLSReport.MxXPath/XLSReport.MxXPath_MxObjectType/MxModelReflection.MxObjectType/CompleteName","readOnlyStyle":"text","attributePath":"XLSReport.MxXPath/XLSReport.MxXPath_MxObjectType/MxModelReflection.MxObjectType/CompleteName","datasource":{"friendlyId":"XLSReport.SN_Xpath_Template.referenceSelector3","type":"xpath","path":"MxModelReflection.MxObjectType","constrainedBy":["XLSReport.MxXPath/XLSReport.MxXPath_MxObjectReference/MxModelReflection.MxObjectReference/MxModelReflection.MxObjectReference_MxObjectType/MxModelReflection.MxObjectType"],"sort":[["CompleteName","asc"]]},"events":{"change":{"type":"callMicroflow","argMap":{"MxXPath":"122_81_111_114_117_120_122"},"config":{"name":"XLSReport.OCh_XPath_Refresh","validate":"node","applyTo":"selection","allowedRoles":["Administrator","User","Tester","DemoAdmin"]}}},"validation":null,"emptyOptionCaption":""' class='mx-name-referenceSelector3' tabindex='0'></div></td></tr></tbody></table></m:template></m:templates></m:page>